ecfg/__init__.py
ecfg/api.py
ecfg/crypto.py
ecfg/key.py
ecfg-0.4.dist-info/DESCRIPTION.rst
ecfg-0.4.dist-info/LICENSE.txt
ecfg-0.4.dist-info/METADATA
ecfg-0.4.dist-info/RECORD
ecfg-0.4.dist-info/WHEEL
ecfg-0.4.dist-info/metadata.json
ecfg-0.4.dist-info/top_level.txt
