Metadata-Version: 2.0
Name: ecfg
Version: 0.4
Summary: Python implementation for Shopify/ecfg
Home-page: https://github.com/pior/ecfg
Author: Pior Bastida
Author-email: pior@pbastida.net
License: MIT
Keywords: secrets ejson crypto
Platform: UNKNOWN
Classifier: Intended Audience :: Developers
Classifier: Programming Language :: Python
Classifier: Programming Language :: Python :: 3.5
Classifier: Programming Language :: Python :: 3.6
Classifier: Programming Language :: Python :: Implementation :: PyPy
Classifier: License :: OSI Approved :: MIT License
Requires-Dist: PyNaCl
